SteelExcel/__init__.py
SteelExcel/main.py
SteelExcel/static/SETTINGS.ini
SteelExcel/static/class2.xlsx
SteelExcel/static/origin.xlsx
SteelExcel/static/申请书提交.xlsx
SteelExcel-0.0.3.dist-info/METADATA
SteelExcel-0.0.3.dist-info/WHEEL
SteelExcel-0.0.3.dist-info/top_level.txt
SteelExcel-0.0.3.dist-info/RECORD
