Metadata-Version: 2.1
Name: SteelExcel
Version: 0.0.3
Summary: A small package for class 2
Home-page: https://github.com/Hifive55555/
Author: Hifive
Author-email: 2019912635@qq.com
License: UNKNOWN
Platform: UNKNOWN
Classifier: Programming Language :: Python :: 3
Classifier: License :: OSI Approved :: MIT License
Classifier: Operating System :: OS Independent
Requires-Python: >=3.8
Requires-Dist: xlwings (>=0.3)
